{"names":["Aimar","Avo","Hania","Herbert","Janusz","Jaś","Joanna & Adam","Magda & Krzysiek","Mihkel","Ola & Kaur","Olle & Kätlin","Paweł","Piotrek","Przemek","Sebastian","Timo"],"matchLabels":[{"m":"Mexico - South Africa","d":"Thu 11.06","r":"2:0"},{"m":"Korea Republic - Czechia","d":"Fri 12.06","r":"2:1"},{"m":"Canada - Bosnia","d":"Fri 12.06","r":"1:1"},{"m":"USA - Paraguay","d":"Sat 13.06","r":"4:1"},{"m":"Qatar - Switzerland","d":"Sat 13.06","r":"1:1"},{"m":"Brazil - Morocco","d":"Sun 14.06","r":"1:1"},{"m":"Haiti - Scotland","d":"Sun 14.06","r":"0:1"},{"m":"Australia - Turkiye","d":"Sun 14.06","r":"2:0"},{"m":"Germany - Curacao","d":"Sun 14.06","r":"7:1"},{"m":"Netherlands - Japan","d":"Sun 14.06","r":"2:2"},{"m":"Ivory Coast - Ecuador","d":"Mon 15.06","r":"1:0"},{"m":"Sweden - Tunisia","d":"Mon 15.06","r":"5:1"},{"m":"Spain - Cape Verde","d":"Mon 15.06","r":"0:0"},{"m":"Belgium - Egypt","d":"Mon 15.06","r":"1:1"},{"m":"Saudi Arabia - Uruguay","d":"Tue 16.06","r":"1:1"},{"m":"Iran - New Zealand","d":"Tue 16.06","r":"2:2"},{"m":"France - Senegal","d":"Tue 16.06","r":"3:1"},{"m":"Iraq - Norway","d":"Wed 17.06","r":"1:4"},{"m":"Argentina - Algeria","d":"Wed 17.06","r":"3:0"},{"m":"Austria - Jordan","d":"Wed 17.06","r":"3:1"},{"m":"Portugal - Congo DR","d":"Wed 17.06","r":"1:1"},{"m":"England - Croatia","d":"Wed 17.06","r":"4:2"},{"m":"Ghana - Panama","d":"Thu 18.06","r":"1:0"},{"m":"Uzbekistan - Colombia","d":"Thu 18.06","r":"1:3"},{"m":"Czechia - South Africa","d":"Thu 18.06","r":"1:1"},{"m":"Switzerland - Bosnia","d":"Thu 18.06","r":"4:1"},{"m":"Canada - Qatar","d":"Fri 19.06","r":"6:0"},{"m":"Mexico - Korea Republic","d":"Fri 19.06","r":"1:0"},{"m":"USA - Australia","d":"Fri 19.06","r":"2:0"},{"m":"Scotland - Morocco","d":"Sat 20.06","r":"0:1"},{"m":"Brazil - Haiti","d":"Sat 20.06","r":"3:0"},{"m":"Turkiye - Paraguay","d":"Sat 20.06","r":"0:1"},{"m":"Netherlands - Sweden","d":"Sat 20.06","r":"5:1"},{"m":"Germany - Ivory Coast","d":"Sat 20.06","r":"2:1"},{"m":"Ecuador - Curacao","d":"Sun 21.06","r":"0:0"},{"m":"Tunisia - Japan","d":"Sun 21.06","r":"0:4"},{"m":"Spain - Saudi Arabia","d":"Sun 21.06","r":"4:0"},{"m":"Belgium - Iran","d":"Sun 21.06","r":"0:0"},{"m":"Uruguay - Cape Verde","d":"Mon 22.06","r":"2:2"},{"m":"New Zealand - Egypt","d":"Mon 22.06","r":"1:3"},{"m":"Argentina - Austria","d":"Mon 22.06","r":"2:0"},{"m":"France - Iraq","d":"Mon 22.06","r":"3:0"},{"m":"Norway - Senegal","d":"Tue 23.06","r":"3:2"},{"m":"Jordan - Algeria","d":"Tue 23.06","r":"1:2"},{"m":"Portugal - Uzbekistan","d":"Tue 23.06","r":"5:0"},{"m":"England - Ghana","d":"Tue 23.06","r":"0:0"},{"m":"Panama - Croatia","d":"Wed 24.06","r":"0:1"},{"m":"Colombia - Congo DR","d":"Wed 24.06","r":"1:0"},{"m":"Switzerland - Canada","d":"Wed 24.06","r":"2:1"},{"m":"Bosnia - Qatar","d":"Wed 24.06","r":"3:1"},{"m":"Scotland - Brazil","d":"Thu 25.06","r":"0:3"},{"m":"Morocco - Haiti","d":"Thu 25.06","r":"4:2"},{"m":"Czechia - Mexico","d":"Thu 25.06","r":"0:3"},{"m":"South Africa - Korea Rep.","d":"Thu 25.06","r":"1:0"},{"m":"Curacao - Ivory Coast","d":"Thu 25.06","r":"0:2"},{"m":"Ecuador - Germany","d":"Thu 25.06","r":"2:1"},{"m":"Japan - Sweden","d":"Fri 26.06","r":"1:1"},{"m":"Tunisia - Netherlands","d":"Fri 26.06","r":"1:3"},{"m":"Turkiye - USA","d":"Fri 26.06","r":"3:2"},{"m":"Paraguay - Australia","d":"Fri 26.06","r":"0:0"},{"m":"Norway - France","d":"Fri 26.06","r":"1:4"},{"m":"Senegal - Iraq","d":"Fri 26.06","r":"5:0"},{"m":"Cape Verde - Saudi Arabia","d":"Sat 27.06","r":"0:0"},{"m":"Uruguay - Spain","d":"Sat 27.06","r":"0:1"},{"m":"Egypt - Iran","d":"Sat 27.06","r":"1:1"},{"m":"New Zealand - Belgium","d":"Sat 27.06","r":"1:5"},{"m":"Panama - England","d":"Sat 27.06","r":"0:2"},{"m":"Croatia - Ghana","d":"Sat 27.06","r":"2:1"},{"m":"Colombia - Portugal","d":"Sun 28.06","r":"0:0"},{"m":"Congo DR - Uzbekistan","d":"Sun 28.06","r":"3:1"},{"m":"Algeria - Austria","d":"Sun 28.06","r":"3:3"},{"m":"Jordan - Argentina","d":"Sun 28.06","r":"1:3"},{"m":"South Africa - Canada","d":"Sun 28.06","r":"0:1"},{"m":"Brazil - Japan","d":"Mon 29.06","r":"2:1"},{"m":"Germany - Paraguay","d":"Mon 29.06","r":"1:1 x"},{"m":"Netherlands - Morocco","d":"Tue 30.06","r":"1:1 x"},{"m":"Ivory Coast - Norway","d":"Tue 30.06","r":"1:2"},{"m":"France - Sweden","d":"Tue 30.06","r":"3:0"},{"m":"Mexico - Ecuador","d":"Wed 1.07","r":"2:0"}],"ptsByPlayer":{"Aimar":[2.0,0.0,0.0,1.0,0.0,0.0,1.0,0.0,1.0,0.0,0.0,1.0,0.0,0.0,0.0,0.0,1.0,1.0,1.0,1.0,0.0,0.0,0.0,1.0,2.0,1.0,1.0,0.0,2.0,2.0,2.0,0.0,1.0,1.0,0.0,1.0,1.0,0.0,0.0,1.0,1.0,2.0,1.0,2.0,1.0,0.0,1.0,2.0,0.0,1.0,1.0,1.0,1.0,0.0,2.0,0.0,2.0,1.0,0.0,2.0,1.0,1.0,1.0,2.0,2.0,1.0,2.0,1.0,0.0,1.0,0.0,1.0,1.0,1.0,0.0,2.0,0.0,1.0,1.0],"Avo":[1.0,0.0,0.0,1.0,0.0,0.0,0.0,0.0,1.0,0.0,0.0,0.0,0.0,0.0,2.0,0.0,1.0,1.0,1.0,1.0,0.0,1.0,2.0,1.0,0.0,0.0,1.0,0.0,2.0,1.0,1.0,0.0,0.0,1.0,0.0,1.0,1.0,0.0,0.0,1.0,1.0,2.0,2.0,1.0,1.0,0.0,1.0,1.0,0.0,1.0,1.0,1.0,1.0,0.0,1.0,0.0,0.0,1.0,0.0,0.0,0.0,1.0,1.0,1.0,0.0,1.0,2.0,0.0,0.0,1.0,1.0,1.0,1.0,2.0,0.0,2.0,1.0,1.0,1.0],"Hania":[1.0,0.0,0.0,1.0,1.0,0.0,1.0,0.0,1.0,0.0,0.0,1.0,0.0,0.0,1.0,1.0,1.0,0.0,1.0,1.0,0.0,0.0,0.0,1.0,0.0,0.0,1.0,0.0,1.0,1.0,2.0,0.0,0.0,1.0,1.0,1.0,1.0,0.0,1.0,0.0,1.0,1.0,0.0,0.0,1.0,0.0,1.0,0.0,0.0,0.0,1.0,1.0,1.0,0.0,1.0,0.0,0.0,1.0,0.0,1.0,1.0,0.0,0.0,1.0,0.0,1.0,1.0,0.0,1.0,0.0,0.0,1.0,1.0,1.0,0.0,0.0,0.0,1.0,1.0],"Herbert":[2.0,0.0,0.0,1.0,0.0,0.0,1.0,0.0,1.0,0.0,0.0,1.0,0.0,0.0,0.0,0.0,2.0,1.0,2.0,1.0,0.0,1.0,0.0,1.0,0.0,1.0,1.0,0.0,1.0,0.0,1.0,0.0,1.0,2.0,0.0,1.0,1.0,0.0,1.0,0.0,1.0,1.0,1.0,1.0,1.0,0.0,1.0,1.0,1.0,1.0,1.0,1.0,0.0,0.0,2.0,0.0,2.0,1.0,0.0,0.0,1.0,1.0,1.0,1.0,2.0,1.0,1.0,0.0,1.0,0.0,0.0,1.0,1.0,1.0,0.0,0.0,0.0,2.0,0.0],"Janusz":[2.0,0.0,2.0,1.0,0.0,0.0,1.0,0.0,1.0,1.0,1.0,1.0,0.0,0.0,0.0,1.0,1.0,1.0,1.0,1.0,0.0,0.0,2.0,1.0,0.0,0.0,1.0,0.0,1.0,1.0,1.0,0.0,0.0,2.0,0.0,1.0,1.0,0.0,1.0,1.0,2.0,1.0,1.0,2.0,1.0,0.0,1.0,1.0,0.0,1.0,1.0,1.0,1.0,0.0,2.0,0.0,1.0,1.0,0.0,1.0,0.0,1.0,1.0,1.0,0.0,1.0,2.0,0.0,0.0,1.0,1.0,1.0,1.0,2.0,0.0,1.0,2.0,1.0,1.0],"Jaś":[1.0,0.0,0.0,1.0,0.0,0.0,0.0,0.0,1.0,0.0,0.0,0.0,0.0,0.0,0.0,1.0,1.0,1.0,2.0,1.0,0.0,0.0,2.0,1.0,0.0,0.0,1.0,0.0,1.0,1.0,2.0,0.0,0.0,1.0,0.0,1.0,1.0,0.0,0.0,1.0,1.0,1.0,1.0,0.0,1.0,0.0,1.0,1.0,0.0,1.0,1.0,1.0,1.0,0.0,1.0,0.0,0.0,1.0,0.0,0.0,1.0,1.0,1.0,1.0,0.0,1.0,1.0,1.0,0.0,1.0,1.0,1.0,1.0,0.0,0.0,1.0,1.0,1.0,1.0],"Joanna & Adam":[2.0,0.0,0.0,1.0,0.0,0.0,1.0,0.0,1.0,0.0,0.0,1.0,0.0,0.0,0.0,0.0,1.0,1.0,1.0,1.0,0.0,1.0,0.0,1.0,0.0,0.0,1.0,1.0,2.0,0.0,1.0,0.0,1.0,2.0,0.0,1.0,1.0,0.0,0.0,1.0,1.0,2.0,0.0,0.0,1.0,0.0,1.0,1.0,1.0,1.0,2.0,1.0,1.0,0.0,1.0,0.0,0.0,1.0,0.0,0.0,1.0,1.0,0.0,1.0,0.0,1.0,2.0,2.0,0.0,1.0,0.0,1.0,1.0,1.0,0.0,0.0,0.0,1.0,0.0],"Magda & Krzysiek":[1.0,0.0,0.0,1.0,0.0,0.0,2.0,0.0,1.0,2.0,0.0,1.0,0.0,0.0,0.0,0.0,2.0,1.0,1.0,1.0,0.0,1.0,0.0,2.0,0.0,1.0,0.0,0.0,1.0,1.0,1.0,0.0,1.0,1.0,0.0,1.0,1.0,1.0,0.0,0.0,1.0,1.0,1.0,1.0,1.0,0.0,0.0,1.0,0.0,1.0,1.0,1.0,1.0,0.0,1.0,0.0,0.0,1.0,0.0,0.0,0.0,1.0,0.0,1.0,0.0,1.0,2.0,1.0,0.0,1.0,0.0,1.0,0.0,0.0,0.0,1.0,1.0,0.0,1.0],"Mihkel":[2.0,1.0,0.0,1.0,0.0,0.0,1.0,0.0,1.0,0.0,0.0,1.0,0.0,0.0,0.0,0.0,1.0,1.0,2.0,1.0,0.0,1.0,1.0,1.0,0.0,0.0,1.0,1.0,1.0,1.0,2.0,0.0,0.0,2.0,0.0,1.0,1.0,1.0,0.0,1.0,1.0,2.0,0.0,1.0,1.0,0.0,1.0,1.0,0.0,0.0,1.0,1.0,1.0,0.0,1.0,0.0,0.0,1.0,0.0,0.0,1.0,1.0,0.0,1.0,2.0,1.0,2.0,2.0,1.0,1.0,0.0,1.0,1.0,1.0,0.0,3.0,2.0,1.0,0.0],"Ola & Kaur":[0.0,0.0,2.0,1.0,0.0,0.0,1.0,0.0,1.0,0.0,0.0,1.0,0.0,0.0,0.0,0.0,1.0,1.0,1.0,1.0,0.0,1.0,0.0,1.0,0.0,1.0,1.0,2.0,1.0,2.0,1.0,0.0,0.0,1.0,0.0,1.0,1.0,0.0,0.0,1.0,1.0,1.0,1.0,0.0,1.0,0.0,1.0,0.0,1.0,1.0,1.0,1.0,1.0,0.0,2.0,0.0,0.0,1.0,0.0,1.0,0.0,1.0,0.0,1.0,1.0,1.0,1.0,2.0,0.0,1.0,0.0,1.0,1.0,0.0,0.0,1.0,1.0,1.0,2.0],"Olle & Kätlin":[1.0,0.0,0.0,1.0,0.0,0.0,1.0,0.0,1.0,0.0,0.0,1.0,0.0,0.0,0.0,1.0,1.0,1.0,1.0,1.0,0.0,1.0,0.0,1.0,0.0,1.0,1.0,0.0,1.0,1.0,1.0,0.0,1.0,1.0,0.0,1.0,1.0,0.0,0.0,1.0,1.0,1.0,0.0,1.0,1.0,0.0,1.0,1.0,0.0,1.0,1.0,1.0,1.0,0.0,2.0,0.0,0.0,1.0,0.0,1.0,1.0,1.0,1.0,1.0,0.0,1.0,1.0,0.0,0.0,1.0,0.0,1.0,1.0,0.0,0.0,2.0,1.0,1.0,1.0],"Paweł":[1.0,0.0,0.0,1.0,0.0,0.0,0.0,0.0,1.0,0.0,0.0,1.0,0.0,0.0,0.0,0.0,1.0,0.0,2.0,0.0,0.0,0.0,0.0,0.0,0.0,1.0,1.0,1.0,0.0,1.0,1.0,0.0,0.0,1.0,0.0,1.0,1.0,0.0,0.0,0.0,1.0,2.0,0.0,1.0,1.0,0.0,1.0,1.0,2.0,0.0,2.0,1.0,0.0,0.0,2.0,0.0,0.0,1.0,0.0,2.0,1.0,1.0,1.0,1.0,2.0,1.0,1.0,2.0,0.0,1.0,0.0,1.0,1.0,0.0,0.0,0.0,1.0,1.0,2.0],"Piotrek":[1.0,0.0,2.0,1.0,0.0,0.0,1.0,0.0,1.0,0.0,0.0,1.0,0.0,0.0,0.0,0.0,0.0,1.0,1.0,1.0,0.0,0.0,0.0,1.0,0.0,0.0,1.0,1.0,0.0,0.0,1.0,0.0,0.0,1.0,0.0,1.0,1.0,0.0,0.0,0.0,1.0,1.0,1.0,1.0,1.0,0.0,1.0,1.0,0.0,1.0,1.0,1.0,1.0,0.0,2.0,0.0,1.0,1.0,0.0,1.0,1.0,1.0,1.0,1.0,2.0,1.0,2.0,1.0,0.0,1.0,1.0,1.0,1.0,2.0,0.0,0.0,2.0,1.0,2.0],"Przemek":[1.0,0.0,0.0,1.0,0.0,0.0,1.0,0.0,1.0,0.0,0.0,1.0,0.0,0.0,0.0,0.0,1.0,1.0,2.0,1.0,0.0,1.0,0.0,1.0,0.0,0.0,1.0,0.0,0.0,1.0,2.0,0.0,1.0,1.0,0.0,1.0,1.0,0.0,0.0,0.0,2.0,1.0,1.0,1.0,1.0,0.0,1.0,1.0,0.0,1.0,1.0,1.0,1.0,0.0,1.0,0.0,2.0,1.0,0.0,1.0,0.0,1.0,0.0,1.0,0.0,1.0,1.0,1.0,0.0,1.0,0.0,1.0,2.0,2.0,0.0,0.0,1.0,0.0,1.0],"Sebastian":[1.0,2.0,0.0,1.0,0.0,1.0,1.0,0.0,1.0,0.0,0.0,1.0,0.0,0.0,0.0,1.0,1.0,1.0,1.0,1.0,0.0,1.0,1.0,1.0,0.0,0.0,0.0,0.0,1.0,1.0,2.0,0.0,0.0,1.0,2.0,1.0,1.0,0.0,0.0,2.0,1.0,2.0,0.0,1.0,1.0,0.0,1.0,0.0,0.0,1.0,1.0,1.0,0.0,0.0,2.0,0.0,1.0,1.0,0.0,1.0,0.0,1.0,1.0,1.0,0.0,1.0,1.0,1.0,1.0,1.0,0.0,1.0,0.0,2.0,0.0,3.0,1.0,1.0,0.0],"Timo":[1.0,0.0,0.0,0.0,0.0,0.0,2.0,0.0,1.0,1.0,0.0,1.0,0.0,0.0,0.0,0.0,1.0,1.0,0.0,1.0,0.0,1.0,1.0,1.0,0.0,0.0,1.0,0.0,1.0,1.0,2.0,0.0,1.0,1.0,0.0,1.0,1.0,0.0,0.0,1.0,1.0,1.0,0.0,1.0,1.0,0.0,1.0,0.0,0.0,1.0,1.0,1.0,1.0,0.0,2.0,0.0,0.0,1.0,0.0,0.0,1.0,1.0,1.0,1.0,0.0,1.0,2.0,1.0,1.0,1.0,1.0,1.0,1.0,2.0,0.0,1.0,2.0,1.0,0.0]},"betsByPlayer":{"Aimar":["2:0","1:1","2:0","1:0","0:2","2:1","0:2","1:2","3:0","2:1","0:1","2:0","3:0","2:1","0:2","2:0","2:0","0:2","2:0","2:0","2:0","1:1","1:1","0:2","1:1","1:0","2:0","1:1","2:0","0:1","3:0","1:1","2:1","2:0","2:0","0:1","3:0","2:0","1:0","0:1","2:1","3:0","2:1","1:2","2:0","2:0","0:2","1:0","1:1","2:0","0:2","2:0","0:1","0:1","0:2","0:2","1:1","0:3","1:1","0:0","1:2","2:0","1:1","0:1","1:1","0:3","0:2","3:1","2:1","1:0","1:0","0:2","1:2","1:0","2:0","x 1:1","1:0","3:1","1:0"],"Avo":["1:0","1:2","0:1","2:0","0:2","2:1","1:0","0:2","3:0","2:1","1:1","0:0","3:0","2:1","1:1","0:1","2:1","0:3","2:1","2:0","2:1","1:0","1:0","0:2","1:0","1:1","2:0","1:2","2:0","1:3","4:0","2:0","2:2","3:1","1:0","0:2","2:1","3:0","2:1","1:2","3:1","3:0","3:2","0:1","2:1","2:0","0:2","2:1","2:2","1:0","1:2","4:0","1:2","0:1","0:1","0:2","2:1","0:4","1:1","1:0","2:1","2:0","1:1","0:2","2:1","0:2","0:2","0:1","1:2","1:0","1:1","0:2","0:2","2:1","2:0","2:2 x","0:3","3:1","1:0"],"Hania":["3:1","1:3","2:0","3:0","2:2","3:1","0:3","1:1","6:0","2:1","1:3","3:0","6:0","4:2","2:2","1:1","5:0","1:1","4:0","3:0","5:1","2:2","2:2","1:2","2:1","1:1","2:1","2:2","2:1","1:2","3:0","3:1","2:2","4:1","2:2","1:3","3:1","1:0","1:1","1:1","2:1","4:1","2:2","3:3","3:0","3:0","0:3","2:2","2:2","1:1","1:3","4:0","1:3","1:2","1:2","0:3","2:1","0:3","0:3","2:2","1:2","1:1","1:0","1:2","2:1","1:2","0:5","1:1","2:2","1:1","1:2","1:5","1:2","3:2","3:1","2:1","2:1","4:1","4:1"],"Herbert":["2:0","0:1","1:0","2:1","0:2","3:0","0:2","1:1","4:0","2:0","1:1","1:0","3:0","1:0","0:2","0:1","3:1","0:2","3:0","1:0","2:0","1:0","1:1","0:2","1:0","1:0","2:0","1:1","2:1","1:0","2:0","2:0","1:0","2:1","2:0","0:1","3:1","1:0","1:1","1:1","1:0","1:0","2:1","0:1","1:0","2:0","1:2","3:0","1:0","1:0","0:1","1:0","1:1","1:1","0:2","1:3","1:1","0:2","1:2","0:1","1:2","2:0","1:1","1:2","1:1","0:1","0:1","1:1","1:1","1:1","1:2","0:1","1:3","2:0","2:0","2:0","1:1 x","3:0","0:0 x"],"Janusz":["2:0","1:1","1:1","1:0","0:2","2:1","0:2","0:2","3:0","1:1","2:1","2:0","3:0","2:0","0:2","1:1","2:1","0:2","2:0","2:0","2:0","1:1","1:0","0:2","2:1","1:1","2:0","1:1","3:1","1:2","2:0","2:1","2:2","2:1","2:0","0:2","2:0","2:0","1:1","1:2","2:0","4:0","2:1","1:2","3:0","2:0","0:2","2:1","2:2","2:0","0:2","2:0","0:2","0:2","0:2","0:1","2:2","0:3","1:1","1:1","1:1","3:0","1:1","0:2","2:1","0:2","0:2","1:1","1:2","2:0","1:1","0:2","0:2","2:1","2:0","x 2:2","1:2","2:0","2:1"],"Jaś":["1:0","1:2","2:1","1:0","0:2","2:1","1:1","0:1","2:0","2:1","1:1","1:1","3:0","2:1","1:2","1:1","2:1","0:2","3:0","1:0","2:0","2:2","1:0","1:2","2:1","1:1","2:1","1:1","2:1","1:2","3:0","2:1","1:2","4:1","2:1","1:2","1:0","2:1","2:1","1:2","3:1","3:1","2:1","0:0","2:0","2:1","0:2","2:1","2:2","2:1","1:3","2:1","1:3","1:2","1:2","1:3","2:3","0:4","1:2","2:1","2:3","3:1","1:1","1:3","2:1","1:2","1:4","3:1","1:4","2:1","2:2","1:4","1:3","x 2:2","3:1","x 2:2","1:3","3:2","2:1"],"Joanna & Adam":["2:0","0:1","1:0","1:0","0:2","2:0","1:2","0:1","5:0","2:1","1:1","1:0","3:0","2:0","0:2","2:0","2:0","0:1","2:1","1:0","2:0","1:0","1:1","0:2","1:0","1:1","2:1","2:1","2:0","1:1","4:0","2:1","2:1","2:1","2:0","0:1","3:0","2:0","2:0","1:2","1:0","3:0","1:1","1:1","3:0","2:1","0:2","2:0","1:0","2:0","0:3","4:0","0:1","0:1","0:3","0:2","0:1","0:2","1:2","1:0","1:2","2:0","0:1","1:2","2:0","0:2","0:2","2:1","1:2","2:0","0:1","0:3","1:2","3:0","3:0","3:0","1:1 x","2:0","x 0:0"],"Magda & Krzysiek":["2:1","1:1","1:0","2:0","1:2","3:2","0:1","1:3","3:0","2:2","1:1","2:0","3:0","2:0","0:2","2:1","3:1","0:2","2:1","3:0","3:1","2:1","1:1","1:3","2:1","1:0","1:1","2:2","2:1","0:2","1:0","2:1","3:2","3:1","2:1","0:2","2:1","1:1","2:0","1:1","3:1","4:0","2:1","0:2","2:1","3:0","2:2","2:0","1:1","1:0","0:1","2:0","1:2","1:2","0:1","0:4","2:1","0:2","0:2","0:1","3:2","1:0","1:0","1:2","2:1","1:2","0:2","3:1","2:1","2:0","1:2","0:3","x 1:1","1:2","3:0","x 2:2","1:3","x 2:2","2:1"],"Mihkel":["2:0","1:0","1:0","2:1","0:3","2:1","0:2","0:1","4:0","2:1","1:1","1:0","3:0","2:0","0:2","2:1","2:1","1:2","3:0","2:0","2:0","2:1","2:1","1:2","1:0","1:1","2:1","2:1","2:1","1:2","3:0","2:1","2:2","2:1","2:0","1:2","2:0","1:1","2:0","1:2","2:1","3:0","1:1","0:2","3:0","2:1","0:2","2:0","1:2","1:1","0:2","2:0","1:2","1:2","0:3","1:2","2:1","0:2","1:2","1:2","1:2","2:0","1:2","1:2","1:1","0:2","0:2","2:1","1:1","2:0","1:2","0:3","1:2","2:0","2:0","1:1 x","1:2","3:1","x 1:1"],"Ola & Kaur":["1:1","1:2","1:1","3:1","1:3","2:1","0:2","0:2","3:0","2:1","0:2","2:0","4:0","1:0","0:2","2:0","2:0","0:2","2:0","1:0","2:0","1:0","0:1","0:2","1:0","1:0","1:0","1:0","2:1","0:1","2:0","1:1","2:2","3:1","2:0","1:2","3:1","2:1","1:2","0:2","3:0","4:0","2:1","1:1","3:0","3:0","0:2","1:1","1:0","1:0","0:2","2:0","0:1","0:1","0:2","0:1","1:0","0:2","1:1","1:1","2:2","2:1","3:1","1:3","2:2","1:2","0:3","2:1","1:2","3:0","0:1","0:2","1:2","x 2:2","3:1","x 2:2","1:3","2:0","2:0"],"Olle & Kätlin":["1:0","0:2","2:1","2:0","0:2","3:0","0:2","1:2","3:0","2:1","1:1","1:0","5:0","3:1","0:2","1:1","2:1","0:2","2:0","1:0","3:0","2:1","1:1","0:2","2:1","2:1","2:0","1:1","2:1","1:3","4:0","1:1","3:1","2:0","2:0","0:1","5:0","2:1","2:0","0:3","3:0","3:1","1:1","0:1","3:0","3:1","1:2","2:1","1:1","3:0","0:2","3:0","1:2","0:2","0:2","1:2","2:1","0:3","0:2","1:1","1:2","1:0","1:1","1:2","2:1","0:2","0:3","1:1","1:3","2:0","0:1","0:4","1:2","x 1:1","2:0","x 1:1","0:1","2:0","2:1"],"Paweł":["3:0","1:1","2:1","2:1","0:3","2:1","0:0","1:1","1:0","2:1","0:0","3:0","4:0","2:1","1:2","3:0","2:0","1:1","3:0","0:0","3:0","2:2","1:1","0:0","2:1","2:1","2:1","2:1","2:2","1:2","2:1","1:1","2:2","3:0","2:0","0:2","2:0","2:1","2:0","2:1","3:0","3:0","1:1","0:2","2:0","3:1","1:2","2:0","2:1","0:0","0:3","2:0","2:2","0:2","0:2","1:3","3:2","0:3","1:2","0:0","1:2","2:0","1:1","0:2","1:1","0:2","0:4","2:1","0:1","2:0","2:1","0:4","1:2","","3:0","3:1","0:2","2:0","2:0"],"Piotrek":["3:1","0:0","1:1","1:0","0:2","2:1","1:3","1:1","4:0","2:1","1:1","1:0","4:0","2:0","0:2","1:3","1:1","1:3","1:0","2:0","3:1","1:1","1:1","0:1","2:1","1:1","3:1","2:1","1:1","0:0","2:0","2:1","2:2","3:1","2:1","0:2","3:0","2:1","2:0","1:1","3:1","4:0","2:1","1:3","2:0","2:0","0:2","2:0","1:1","3:0","0:2","2:0","1:2","1:1","0:2","1:3","2:2","0:3","1:2","1:1","1:2","2:0","1:1","1:2","1:1","0:2","0:2","1:0","1:2","2:1","1:1","0:3","0:2","2:1","2:0","2:1","1:2","3:1","2:0"],"Przemek":["3:1","1:2","2:0","2:1","0:2","4:0","0:2","1:3","5:0","1:0","0:2","2:0","4:0","2:1","1:2","1:0","2:0","0:2","3:0","2:1","2:0","3:0","1:2","0:2","2:0","1:1","1:0","1:1","2:2","1:2","3:0","1:1","2:1","3:0","2:0","0:2","3:0","2:1","2:0","2:1","2:0","2:0","2:1","0:1","2:0","3:0","0:2","2:1","1:1","1:0","0:2","2:0","0:2","1:2","0:1","1:2","1:1","0:2","1:2","1:1","1:1","2:1","2:1","0:2","2:1","1:2","0:3","2:0","1:2","2:0","0:2","0:4","0:1","2:1","3:1","2:1","0:2","x 1:1","2:1"],"Sebastian":["3:1","2:1","2:0","2:1","0:3","2:2","0:2","0:3","6:0","1:2","2:2","2:0","7:0","4:1","0:4","0:0","4:1","0:3","2:1","4:0","3:0","2:0","3:1","0:4","2:0","0:1","1:1","0:2","3:1","0:3","3:0","1:1","2:2","3:0","0:0","0:3","3:1","4:0","2:0","1:3","3:0","3:0","2:2","0:3","4:0","3:2","0:3","1:2","1:1","2:0","1:3","3:0","2:0","1:2","0:2","1:3","2:2","0:4","0:2","1:1","3:1","3:0","1:1","0:3","2:0","1:2","0:5","3:2","1:1","3:0","0:2","0:3","2:0","2:1","5:0","1:1 x","2:3","4:1","0:0 x"],"Timo":["2:1","0:3","0:2","1:2","0:3","2:0","0:1","1:2","3:0","1:1","1:2","2:0","3:0","2:1","0:2","1:0","2:1","0:3","2:2","2:0","3:0","2:1","2:1","0:2","2:1","1:1","2:0","2:2","2:1","1:2","3:0","2:1","2:1","3:1","2:0","1:3","2:0","2:0","2:1","1:2","2:1","4:0","2:2","1:3","3:0","2:0","0:2","1:1","1:1","2:1","1:3","3:0","1:2","0:1","0:2","0:2","2:1","0:3","1:1","1:2","1:2","3:1","1:1","1:3","2:1","1:2","0:2","1:0","2:2","2:0","1:1","0:4","1:2","2:1","2:0","x 2:2","1:2","2:0","x 1:1"]},"total":{"Aimar":66.0,"Avo":54.0,"Hania":42.0,"Herbert":54.0,"Janusz":63.0,"Jaś":48.0,"Joanna & Adam":50.0,"Magda & Krzysiek":48.0,"Mihkel":60.0,"Ola & Kaur":53.0,"Olle & Kätlin":50.0,"Paweł":49.0,"Piotrek":54.0,"Przemek":50.0,"Sebastian":57.0,"Timo":53.0},"exact":{"Aimar":15,"Avo":8,"Hania":1,"Herbert":8,"Janusz":10,"Jaś":3,"Joanna & Adam":7,"Magda & Krzysiek":5,"Mihkel":9,"Ola & Kaur":6,"Olle & Kätlin":2,"Paweł":9,"Piotrek":7,"Przemek":6,"Sebastian":7,"Timo":6},"correct":{"Aimar":51,"Avo":46,"Hania":41,"Herbert":46,"Janusz":53,"Jaś":45,"Joanna & Adam":43,"Magda & Krzysiek":43,"Mihkel":49,"Ola & Kaur":47,"Olle & Kätlin":48,"Paweł":40,"Piotrek":47,"Przemek":44,"Sebastian":48,"Timo":47},"champ":{"Aimar":"France","Avo":"Norway","Hania":"France","Herbert":"England","Janusz":"France","Jaś":"Argentina","Joanna & Adam":"Spain","Magda & Krzysiek":"Japan","Mihkel":"France","Ola & Kaur":"Argentina","Olle & Kätlin":"France","Paweł":"Argentina","Piotrek":"France","Przemek":"Argentina","Sebastian":"France","Timo":"France"},"nMatches":79,"updatedAt":"2026-07-01T17:00:01+03:00"}
